{
  "title": "European Countries by Population",
  "upperLabel": "Most Populated",
  "lowerLabel": "Least Populated",
  "hint": "Sort European countries from highest to lowest population (2023 estimates)",
  "items": [
    "Germany",
    "United Kingdom", 
    "France",
    "Italy",
    "Spain",
    "Poland",
    "Netherlands",
    "Belgium",
    "Czech Republic",
    "Portugal",
    "Greece",
    "Hungary",
    "Sweden",
    "Austria",
    "Switzerland",
    "Denmark",
    "Finland",
    "Norway",
    "Ireland",
    "Luxembourg"
  ]
} 